<?xml version="1.0" encoding="UTF-8"?>
<AdsDefinition xmlns="http://schemas.radixware.org/adsdef.xsd" FormatVersion="0">
  <AdsLocalizingBundleDefinition Id="mlbadcWAGVG6ZHCVAHVIRIHGK4U33EXY">
    <String Id="mlsESSBHYA2ORF4PGEXDOYYO3T5DQ" SrcKind="1" Creator="npopov" CreationDate="2015-08-03T14:45:20.201" Version="0">
      <Value Language="en" NeedsCheck="true" Agreed="false">Time</Value>
    </String>
    <String Id="mlsMBIK2XJAJFHMXNW2HMNETAFVEM" SrcKind="1" Creator="npopov" CreationDate="2015-08-03T14:45:20.201" Version="0">
      <Value Language="en" NeedsCheck="true" Agreed="false">Value</Value>
    </String>
  </AdsLocalizingBundleDefinition>
</AdsDefinition>