<?xml version="1.0" encoding="UTF-8"?>
<AdsDefinition xmlns="http://schemas.radixware.org/adsdef.xsd" FormatVersion="0">
  <AdsLocalizingBundleDefinition Id="mlbagcHQSOHRWZH5ESLD2Y6IVF6XFBE4">
    <String Id="mlsAKRQKXWHI5GVTHYF6QCFIFBXFU" SrcKind="1" Version="0">
      <Value Language="en" NeedsCheck="false">Exporting...</Value>
    </String>
    <String Id="mlsCGBEGHQWWFDSVMLYQGZWMEDU64" SrcKind="1" Version="0">
      <Value Language="en" NeedsCheck="false">Export Filters</Value>
    </String>
    <String Id="mlsNHGPAYZU55GZTOTPGTDH5CK27U" SrcKind="1" Version="0">
      <Value Language="en" NeedsCheck="false">File not defined</Value>
    </String>
    <String Id="mlsQJJJ4E6PLFDXBOQDJHE5NNAGWM" SrcKind="1" Version="0">
      <Value Language="en" NeedsCheck="false">Failed to export filters</Value>
    </String>
  </AdsLocalizingBundleDefinition>
</AdsDefinition>