<?xml version="1.0" encoding="UTF-8"?>
<AdsDefinition xmlns="http://schemas.radixware.org/adsdef.xsd" FormatVersion="0">
  <AdsClassDefinition Id="aic7DHWELGE5JC77EQ7DBEQLRASF4" Name="IExplorerSelectorWidget" Type="5" Environment="explorer">
    <AccessRules>
      <Transparence Extendable="false" PublishedName="org.radixware.kernel.explorer.widgets.selector.IExplorerSelectorWidget"/>
    </AccessRules>
    <Headers>
      <Src Name="HeaderadcHRZYDUAIDZEITO4HN6BK4D3HNQ"/>
    </Headers>
    <Bodies>
      <Src Name="BodyadcIBWTOXM62VD2LJ67LR4DFYSAVU"/>
    </Bodies>
    <MethodGroup Id="cmgNDVCCEA2GZH2NOBXTQ463AOQMQ" Name="Root"/>
    <PropertyGroup Id="cpgGXTUE5KUDJA3JIYASHMYJMLXRI" Name="Root"/>
    <Properties/>
    <Methods>
      <Method Id="mthOG2UGQSLRZDNFNXKXL5XCBZWEQ" Name="asQWidget" Nature="0" IsOverride="false">
        <AccessRules>
          <Transparence Extendable="false" PublishedName="asQWidget()Lcom.trolltech.qt.gui.QWidget;"/>
        </AccessRules>
        <ReturnType TypeId="400" extStr="com.trolltech.qt.gui.QWidget"/>
      </Method>
    </Methods>
  </AdsClassDefinition>
</AdsDefinition>