<?xml version="1.0" encoding="UTF-8"?>
<AdsDefinition xmlns="http://schemas.radixware.org/adsdef.xsd" FormatVersion="0">
  <AdsLocalizingBundleDefinition Id="mlbaecJ6SOXKD3ZHOBDCMTAALOMT5GDM">
    <String Id="mls2X4FBYL2FVDJTL5JF775ZP4URM" SrcKind="1" Version="0">
      <Value Language="ru" NeedsCheck="false" LastModified="2014-07-07T09:59:37.386" Author="ypaliy">Требуемая версия</Value>
    </String>
    <String Id="mls2ZRQY5J2HZDJJOX6KRXGTLD4XM" SrcKind="1" Version="0">
      <Value Language="ru" NeedsCheck="false" LastModified="2014-07-07T09:59:42.316" Author="ypaliy">GUID класса</Value>
    </String>
    <String Id="mls3DD5OOELGNH4HDEN56MUVX3UXU" SrcKind="1" Creator="npopov" CreationDate="2016-02-24T19:27:33.273" Version="0">
      <Value Language="ru" NeedsCheck="false">функций экспортировано</Value>
    </String>
    <String Id="mls3RO5MJ4H7VEWLNSDXWWIYDJZJY" SrcKind="1" CreationDate="1970-01-01T05:00:00.000" Version="0">
      <Value Language="ru" NeedsCheck="true" LastModified="2014-12-02T14:53:29.556" Author="akrylov">Файл поврежден или не является файлом описания изменений API</Value>
    </String>
    <String Id="mls4N3LV2N2DRHFXLYRA4YYKT3LMQ" SrcKind="1" Version="0">
      <Value Language="ru" NeedsCheck="false" LastModified="2014-07-07T09:59:46.189" Author="ypaliy">upOwnerEntityId</Value>
    </String>
    <String Id="mls4S5LW36FXRB5HEZ47HTT2RTVUU" SrcKind="1" CreationDate="1970-01-01T05:00:00.000" Version="0">
      <Value Language="ru" NeedsCheck="false">XML файлы (*.xml)</Value>
    </String>
    <String Id="mls4V5ZNMWH4VEDVDW63ZAORWTPUM" SrcKind="1" Version="0">
      <Value Language="ru" NeedsCheck="false" LastModified="2014-07-07T09:59:53.847" Author="ypaliy">&lt;функция определена></Value>
    </String>
    <String Id="mls53PZY46IXFFORNNC64KWN6FW5A" SrcKind="1" Version="0">
      <Value Language="ru" NeedsCheck="false" LastModified="2014-07-07T09:59:57.298" Author="ypaliy">Класс владельца</Value>
    </String>
    <String Id="mls5E2HRFXX5VACVNVBS3Q42VZPNE" SrcKind="1" CreationDate="1970-01-01T05:00:00.000" Version="0">
      <Value Language="ru" NeedsCheck="true" LastModified="2014-12-02T14:50:51.549" Author="akrylov">Укажите файл описания изменений API</Value>
    </String>
    <String Id="mls5KYAWGVTP5FJ5ONEYFPYT346O4" SrcKind="1" Creator="npopov" CreationDate="2015-07-03T15:14:30.825" Version="0">
      <Value Language="ru" NeedsCheck="true" LastModified="2015-07-03T15:19:21.436" Author="npopov">Компиляция была отменена.</Value>
    </String>
    <String Id="mls5VAJ54P6BFDALEWYD3F3NQKQAU" SrcKind="3" Creator="akrylov" CreationDate="2014-08-18T12:46:33.744" Version="0">
      <Value Language="ru" NeedsCheck="true" LastModified="2014-08-18T12:46:52.188" Author="akrylov">Владелец - библиотечная функция (может быть null)</Value>
    </String>
    <String Id="mls62NPHG2O6RAPZIP7IKPBG2BCI4" SrcKind="1" Version="0">
      <Value Language="ru" NeedsCheck="false" LastModified="2014-05-29T16:26:04.278" Author="ypaliy">Откомпилирована</Value>
    </String>
    <String Id="mls6AVHPGASQZCQLDCTZQKAIXH6SI" SrcKind="1" Creator="npopov" CreationDate="2015-07-03T14:28:13.230" Version="0">
      <Value Language="ru" NeedsCheck="true" LastModified="2015-07-03T14:28:30.605" Author="npopov">Скомпилировать всё</Value>
    </String>
    <String Id="mls6GFSHIGRJ5DCRKR7DG32T46ZAM" SrcKind="1" CreationDate="1970-01-01T05:00:00.000" Version="0">
      <Value Language="ru" NeedsCheck="false" LastModified="2014-10-28T16:58:20.456" Author="ypaliy">Циклическое связывание. Возможна бесконечная рекурсия</Value>
    </String>
    <String Id="mls72ZCCCQQPBCWXNZVAXOHBETBSM" SrcKind="3" Creator="akrylov" CreationDate="2015-03-27T09:36:43.216" Version="0"/>
    <String Id="mls74E3G6TYZNA4PITYCHNGV6R4DI" SrcKind="1" Version="0">
      <Value Language="ru" NeedsCheck="false" LastModified="2015-05-25T15:19:53.487" Author="ypaliy">Подтверждение удаления объекта</Value>
    </String>
    <String Id="mls74ZZH6U2HJDFTPAULLFFTG62SU" SrcKind="1" Creator="npopov" CreationDate="2015-07-03T14:28:40.683" Version="0">
      <Value Language="ru" NeedsCheck="false">Компиляция завершена!</Value>
    </String>
    <String Id="mls7GOZXWY34VA6TJBU7GNY2IEOBE" SrcKind="1" CreationDate="1970-01-01T05:00:00.000" Version="0">
      <Value Language="ru" NeedsCheck="false" LastModified="2015-04-03T15:44:06.419" Author="ypaliy">Валидация завершена!</Value>
    </String>
    <String Id="mls7WRENQIAR5EDTPAQD626WDWRZU" SrcKind="1" Creator="akrylov" CreationDate="2015-03-27T09:39:43.315" Version="0">
      <Value Language="ru" NeedsCheck="false" LastModified="2015-05-25T15:19:36.820" Author="ypaliy">Текст</Value>
    </String>
    <String Id="mls7XD4EC4XZHOBDCMTAALOMT5GDM" SrcKind="1" Version="0">
      <Value Language="ru" NeedsCheck="false" LastModified="2015-04-01T16:53:59.257" Author="ypaliy">Автор модификации</Value>
    </String>
    <String Id="mlsAMZ33LWJCREW5N65KVIJEIBOAI" SrcKind="1" CreationDate="1970-01-01T05:00:00.000" Version="0">
      <Value Language="ru" NeedsCheck="true">Проверка обнаружила ошибки. Вы действительно хотите продолжить?</Value>
    </String>
    <String Id="mlsBARCF67KSJAKRFXZWBPRBHYRM4" SrcKind="1" Creator="akrylov" CreationDate="2015-06-18T12:34:02.707" Version="0">
      <Value Language="ru" NeedsCheck="true" LastModified="2015-06-18T12:34:13.816" Author="akrylov">Ид.</Value>
    </String>
    <String Id="mlsBS34NDDHQFEB7GFI4WTS5Q2LLI" SrcKind="1" Creator="npopov" CreationDate="2016-02-24T19:25:34.632" Version="0">
      <Value Language="ru" NeedsCheck="false">XML файлы (*.xml)</Value>
    </String>
    <String Id="mlsBV63MAUXZHOBDCMTAALOMT5GDM" SrcKind="1" Version="0">
      <Value Language="ru" NeedsCheck="true" LastModified="2013-09-25T17:18:46.955" Author="akrylov">Время модификации</Value>
    </String>
    <String Id="mlsCVWF5UUWZHOBDCMTAALOMT5GDM" SrcKind="1" Version="0">
      <Value Language="ru" NeedsCheck="true" LastModified="2013-09-25T17:18:46.955" Author="akrylov">Другой исходный код</Value>
    </String>
    <String Id="mlsD5BW5C77CNC2XLXQDTTPLCWR7M" SrcKind="1" Creator="akrylov" CreationDate="2015-06-18T12:34:17.519" Version="0">
      <Value Language="ru" NeedsCheck="true" LastModified="2015-06-18T12:34:39.656" Author="akrylov">Идентификатор функции</Value>
    </String>
    <String Id="mlsDDD4RAU3VBCHLCFIGJP6BBQFGM" SrcKind="1" Creator="akaptsan" CreationDate="2016-02-08T15:38:24.557" Version="0">
      <Value Language="ru" NeedsCheck="false">Ошибка при импорте пользовательской функции</Value>
    </String>
    <String Id="mlsDNXNYRJEPND5NLJF3ON36TY6XI" SrcKind="1" Version="0">
      <Value Language="ru" NeedsCheck="false" LastModified="2014-07-07T10:00:20.888" Author="ypaliy">Пользовательская функция</Value>
    </String>
    <String Id="mlsDSKYHRHE3JDSDEC75Z3I6HHNWU" SrcKind="1" Version="0">
      <Value Language="ru" NeedsCheck="false" LastModified="2014-07-07T10:00:24.661" Author="ypaliy">Профиль</Value>
    </String>
    <String Id="mlsEDM2XOF4OVEAXOFRPPIOBJ465E" SrcKind="1" CreationDate="1970-01-01T05:00:00.000" Version="0">
      <Value Language="ru" NeedsCheck="true">Функция некорректна</Value>
    </String>
    <String Id="mlsEIRMIQ7DRVDJXC2TU6SSE4I3BQ" SrcKind="1" Creator="npopov" CreationDate="2016-02-24T19:27:33.273" Version="0">
      <Value Language="ru" NeedsCheck="false">Экспорт</Value>
    </String>
    <String Id="mlsF35DBJSWBJGXROMXORQGF5JMR4" SrcKind="1" Creator="npopov" CreationDate="2016-02-24T19:25:34.632" Version="0">
      <Value Language="ru" NeedsCheck="false">Сохранить файл</Value>
    </String>
    <String Id="mlsFEVTY3TYBVC43OGRLRICVHGUQQ" SrcKind="1" Creator="akrylov" CreationDate="2014-08-19T10:07:20.099" Version="0">
      <Value Language="ru" NeedsCheck="true" LastModified="2014-08-25T16:22:25.798" Author="akrylov">Код</Value>
    </String>
    <String Id="mlsFU7IVGEOOFCD3JV6JWKYXSFIVY" SrcKind="1" Creator="npopov" CreationDate="2016-02-24T19:27:33.273" Version="0">
      <Value Language="ru" NeedsCheck="false">Экспорт</Value>
    </String>
    <String Id="mlsGEHBZDSFMFDWZBRDLKNKYBOVXQ" SrcKind="1" Creator="npopov" CreationDate="2016-02-24T19:27:33.273" Version="0">
      <Value Language="ru" NeedsCheck="false">Не экспортировано ни одной функции</Value>
    </String>
    <String Id="mlsGKNFFLGI2ZACHERCDHLX72BUAI" SrcKind="1" Version="0">
      <Value Language="ru" NeedsCheck="false" LastModified="2015-05-25T15:19:04.934" Author="ypaliy">Описание</Value>
    </String>
    <String Id="mlsHYSD462P5JD5BGAIFIZBMHDQBI" SrcKind="1" Creator="akaptsan" CreationDate="2015-05-30T15:52:14.474" Version="0">
      <Value Language="ru" NeedsCheck="true">Невалидная функция "</Value></String><String Id="mlsICTXSCUUYNHDLDERQPVNOLIGHY" SrcKind="3" Creator="akrylov" CreationDate="2015-05-07T12:31:35.040" Version="0"/><String Id="mlsIVSB22MX6FBOLBVMABUIXK4S2Y" SrcKind="2" Version="0" EventSource="App.Audit" EventSeverity="1"><Value Language="ru" NeedsCheck="false" LastModified="2015-05-25T15:18:59.772" Author="ypaliy">Пользователь "%1" изменил пользовательскую функцию "%2"</Value></String><String Id="mlsJ4EBVNECQJH77P5MHNLQYEQLOA" SrcKind="1" Creator="akrylov" CreationDate="2015-06-26T10:07:50.613" Version="0"><Value Language="ru" NeedsCheck="false" LastModified="2015-11-18T13:55:20.613" Author="ypaliy">По идентификатору</Value></String><String Id="mlsJJFYGCCXBZAI7OWHG63SKXU3OY" SrcKind="1" Version="0"><Value Language="ru" NeedsCheck="true" LastModified="2013-09-25T17:18:46.955" Author="akrylov">По времени модификации</Value></String><String Id="mlsJR667VUAAZHGLMOTJY6OMJBPFM" SrcKind="1" Version="0"><Value Language="ru" NeedsCheck="false" LastModified="2015-05-25T15:18:40.236" Author="ypaliy">&lt;исходный метод не найден></Value></String><String Id="mlsKNZKVTMXZHOBDCMTAALOMT5GDM" SrcKind="1" Version="0"><Value Language="ru" NeedsCheck="false" LastModified="2014-07-07T10:00:47.398" Author="ypaliy">Пользовательские функции</Value></String><String Id="mlsKRMQOS63QNASDME57SUM7EFE2E" SrcKind="1" Creator="akrylov" CreationDate="2014-08-20T09:26:55.375" Version="0"><Value Language="ru" NeedsCheck="true" LastModified="2014-08-20T09:27:09.351" Author="akrylov">Код можно править</Value></String><String Id="mlsLEIFVQYTCRCR7O5LQRVK5NPKFA" SrcKind="1" Creator="akrylov" CreationDate="2015-06-18T12:35:45.338" Version="0"><Value Language="ru" NeedsCheck="false" LastModified="2015-11-18T13:57:16.725" Author="ypaliy">Ид. функции</Value></String><String Id="mlsMJET4FUYTFDELDVA5FDANT7DUE" SrcKind="1" Version="0"><Value Language="ru" NeedsCheck="false" LastModified="2014-07-07T10:00:50.980" Author="ypaliy">Ид. метода</Value></String><String Id="mlsML67B7EKHFE4DGNS6RTOX2NZNY" SrcKind="1" Version="0"><Value Language="ru" NeedsCheck="true" LastModified="2013-09-25T17:18:46.955" Author="akrylov">Фактическая версия</Value></String><String Id="mlsN3TRK2C3YVB5DO3E466THNJA2A" SrcKind="1" Version="0"><Value Language="ru" NeedsCheck="false" LastModified="2014-11-17T15:11:34.974" Author="ypaliy">Вы действительно хотите удалить</Value></String><String Id="mlsNGONIZIIEBC55PWT6HDFZUYDQI" SrcKind="1" Version="0"><Value Language="ru" NeedsCheck="false" LastModified="2014-07-07T10:01:08.837" Author="ypaliy">Ид. библиотечной функции</Value></String><String Id="mlsO3V6WNHN3ND7FMKIILN5JVPFRY" SrcKind="1" Version="0"><Value Language="ru" NeedsCheck="false" LastModified="2013-12-24T10:45:19.884" Author="ypaliy">Владелец пользовательской функции не существует</Value></String><String Id="mlsOFA44NLVNJCA7DBT2VCDOM3A5Y" SrcKind="1" Version="0"><Value Language="ru" NeedsCheck="false" LastModified="2014-07-07T10:01:26.515" Author="ypaliy">upOwnerClassId</Value></String><String Id="mlsOKGDO5Q43FBIXDPC6NQBTBNGOM" SrcKind="1" Version="0"><Value Language="ru" NeedsCheck="true" LastModified="2013-09-25T17:18:46.955" Author="akrylov">&lt;владелец не найден, PID </Value></String><String Id="mlsPK4O44NEJ5ANBIL2CFSAIQBCZM" SrcKind="1" Creator="aalexeeva" CreationDate="2014-07-14T12:02:11.293" Version="0"><Value Language="ru" NeedsCheck="false" LastModified="2014-10-28T14:56:37.882" Author="ypaliy">Связать с библиотечной функцией</Value></String><String Id="mlsQKET7J6H2RHVPMW6OPVRQ5ZUFU" SrcKind="1" Version="0"><Value Language="ru" NeedsCheck="false" LastModified="2013-12-24T10:50:11.527" Author="ypaliy">Владелец</Value></String><String Id="mlsRTIXYU5XQZBVJPCK4OZI6JBNKM" SrcKind="1" Version="0"><Value Language="ru" NeedsCheck="false" LastModified="2015-09-22T14:47:05.726" Author="ypaliy">Не откомпилированные или содержащие ошибки</Value></String><String Id="mlsSU5SDN2ZOFGKTEVQH5NY6BOD64" SrcKind="1" Creator="akrylov" CreationDate="2014-10-21T09:17:17.576" Version="0"><Value Language="ru" NeedsCheck="false" LastModified="2014-10-28T16:58:03.196" Author="ypaliy">Циклическое связывание. Возможна бесконечная рекурсия</Value></String><String Id="mlsSUXRA2ZYCVEUXFPRVQHFZPOIRE" SrcKind="1" Version="0"><Value Language="ru" NeedsCheck="true" LastModified="2013-09-25T17:18:46.955" Author="akrylov">Информация времени исполнения</Value></String><String Id="mlsTCMXJLZWWJCLNF3YYF7BMLSSWU" SrcKind="1" Creator="akrylov" CreationDate="2015-06-18T12:35:01.825" Version="0"><Value Language="ru" NeedsCheck="false" LastModified="2015-11-18T13:55:28.409" Author="ypaliy">По идентификатору.</Value></String><String Id="mlsVXUGMTUUGNE6LLFEVUEY34AMAU" SrcKind="1" Version="0"><Value Language="ru" NeedsCheck="false" LastModified="2015-09-22T14:47:36.230" Author="ypaliy">Неописанные</Value></String><String Id="mlsW7LYHXK53FHL7AWV3I6STSEVR4" SrcKind="1" Version="0"><Value Language="ru" NeedsCheck="false" LastModified="2014-07-07T10:01:38.266" Author="ypaliy">upOwnerPid</Value></String><String Id="mlsWTEHTIAQBRHVZFDONBUORXOZS4" SrcKind="1" Creator="akrylov" CreationDate="2014-09-03T10:54:24.458" Version="0"><Value Language="ru" NeedsCheck="false" LastModified="2014-10-28T13:33:23.596" Author="ypaliy">Преобразовать в библиотечную функцию</Value></String><String Id="mlsWUMB3KKA6ZA63APKRKZLUGG7RI" SrcKind="1" Version="0"><Value Language="ru" NeedsCheck="false" LastModified="2014-07-07T10:01:42.955" Author="ypaliy">Пользовательская функция</Value></String><String Id="mlsX3M2EUJPEBC6VP6GJEFH7RLBFA" SrcKind="1" Creator="akrylov" CreationDate="2014-12-02T14:52:09.402" Version="0"><Value Language="ru" NeedsCheck="false" LastModified="2015-04-03T16:38:14.316" Author="ypaliy">Не удалось прочитать файл описания изменений API</Value></String><String Id="mlsY2G2XCQ53BH6ZCKSJVBJVFTGOA" SrcKind="1" Version="0"><Value Language="ru" NeedsCheck="false" LastModified="2014-07-07T10:01:48.609" Author="ypaliy">Свойство владельца</Value></String><String Id="mlsYLOVLXP7OZD4PEOT6JHBHHD7HQ" SrcKind="3" Creator="akrylov" CreationDate="2015-12-08T12:23:31.225" Version="0"><Value Language="ru" NeedsCheck="false" LastModified="2015-12-22T12:06:01.805" Author="ypaliy">Базовый класс, описывающий хранение пользовательской функции, предоставляет служебные методы для компиляции, загрузки, сохранения и редактирования пользовательских функций</Value></String><String Id="mlsZNAHTKFXBRBAFFOLDXF2NJP4H4" SrcKind="1" Creator="akrylov" CreationDate="2015-03-27T09:36:16.164" Version="0"><Value Language="ru" NeedsCheck="false" LastModified="2015-09-22T15:08:28.757" Author="ypaliy">По тексту</Value></String><String Id="mlsZUAWK5V3IZE2PD25UDIX3V6BIE" SrcKind="1" Version="0"><Value Language="ru" NeedsCheck="false" LastModified="2014-07-07T10:01:56.881" Author="ypaliy">upDefId</Value></String><String Id="mlsZUV3IEIL7FCCPNWBF3O4BHG5FQ" SrcKind="1" Version="0"><Value Language="ru" NeedsCheck="false" LastModified="2014-07-07T10:02:37.736" Author="ypaliy">GUID пользовательского класса</Value></String><String Id="mlsZVMPR4UWZHOBDCMTAALOMT5GDM" SrcKind="1" Version="0"><Value Language="ru" NeedsCheck="false" LastModified="2014-07-07T10:02:47.013" Author="ypaliy">Java исходный код</Value></String></AdsLocalizingBundleDefinition></AdsDefinition>