<?xml version="1.0" encoding="UTF-8"?>
<AdsDefinition xmlns="http://schemas.radixware.org/adsdef.xsd" FormatVersion="0">
  <AdsLocalizingBundleDefinition Id="mlbacsYING7OYUJ3NRDAQSABIFNQAAAE">
    <String Id="mls45SC4BU4MBDUVO5EHHPIXCOIII" SrcKind="1" Version="0">
      <Value Language="en" NeedsCheck="false" Agreed="false">Very high</Value>
    </String>
    <String Id="mls4D3HLVLGRRC4BM6UKKHKZMKDDI" SrcKind="1" Version="0">
      <Value Language="en" NeedsCheck="false" Agreed="false">Very low</Value>
    </String>
    <String Id="mls4GQANCVXBJCPJBUVDHLNZ4MVGI" SrcKind="1" Version="0">
      <Value Language="en" NeedsCheck="false" Agreed="false">Low</Value>
    </String>
    <String Id="mlsBGDROZKJRNG5JNJNZAXVLNDGFY" SrcKind="1" Version="0">
      <Value Language="en" NeedsCheck="false" Agreed="false">High</Value>
    </String>
    <String Id="mlsBTTZWV3TL5AIHF243K5UPFQFZE" SrcKind="1" Version="0">
      <Value Language="en" NeedsCheck="false" Agreed="false">Idle</Value>
    </String>
    <String Id="mlsDMKTTAFAABEQXKAT7J5XDTESAM" SrcKind="1" Version="0">
      <Value Language="en" NeedsCheck="false" Agreed="false">Above normal</Value>
    </String>
    <String Id="mlsDUVQZV5PEFEO7CYQJXBNNCZAKE" SrcKind="1" Version="0">
      <Value Language="en" NeedsCheck="false" Agreed="false">Below normal</Value>
    </String>
    <String Id="mlsJ3KRVD32VVGILE36WGOKSE3GDU" SrcKind="1" Version="0">
      <Value Language="en" NeedsCheck="false" Agreed="false">Normal</Value>
    </String>
    <String Id="mlsOQUGZHTAFNAPPCRXCAHA3TYU34" SrcKind="3" Creator="dsafonov" CreationDate="2017-01-25T16:11:27.818" Version="0">
      <Value Language="en" NeedsCheck="false" Agreed="false" Version="1" LastModified="2017-12-21T16:20:31.491" Author="ypaliy">Priority</Value>
    </String>
    <String Id="mlsZKENZRNKW5H55FTIGCNFQUNRYQ" SrcKind="1" Version="0">
      <Value Language="en" NeedsCheck="false" Agreed="false">Critical</Value>
    </String>
  </AdsLocalizingBundleDefinition>
</AdsDefinition>