<?xml version="1.0" encoding="UTF-8"?>
<AdsDefinition xmlns="http://schemas.radixware.org/adsdef.xsd" FormatVersion="0">
  <AdsLocalizingBundleDefinition Id="mlbaclFKCYABVIK7OBDCJAAALOMT5GDM">
    <String Id="mls4CFH2IVWG5FIHLQLUDFBAQ5AK4" SrcKind="1" Version="0">
      <Value Language="ru" NeedsCheck="true" LastModified="2013-10-01T10:26:11.656" Author="dsafonov">Ошибка чтения списка ключей из хранилища: </Value>
    </String>
    <String Id="mls4EUVQOK4OXOBDFKUAAMPGXUWTQ" SrcKind="1" Version="0">
      <Value Language="ru" NeedsCheck="false" LastModified="2014-10-22T16:58:07.704" Author="ypaliy">ARTE</Value>
    </String>
    <String Id="mls53ZESOCQL5AL5NHOXQ6UAV3ADY" SrcKind="1" Version="0">
      <Value Language="ru" NeedsCheck="true" LastModified="2013-10-01T10:26:11.656" Author="dsafonov">Ошибка чтения списка ключей из хранилища: </Value>
    </String>
    <String Id="mls6N6MJFIM4JA7RAXGRCX2S7E5DY" SrcKind="1" Version="0">
      <Value Language="ru" NeedsCheck="true" LastModified="2013-10-01T10:26:11.656" Author="dsafonov">Реализуемый сервис</Value>
    </String>
    <String Id="mls7JJ5W4XH3NC73HGMVD7LWUROAU" SrcKind="1" Version="0">
      <Value Language="ru" NeedsCheck="false" LastModified="2014-11-24T16:27:56.538" Author="ypaliy">Сервис</Value>
    </String>
    <String Id="mlsAF5V3G7GNZEABK5MLM2CRLZ7WQ" SrcKind="1" Version="0">
      <Value Language="ru" NeedsCheck="false" LastModified="2014-10-22T16:58:26.115" Author="ypaliy">Среднее количество используемых инстанций ARTE</Value>
    </String>
    <String Id="mlsAUUVQOK4OXOBDFKUAAMPGXUWTQ" SrcKind="1" Version="0">
      <Value Language="ru" NeedsCheck="false" LastModified="2014-11-24T16:27:48.278" Author="ypaliy">Параметры точки доступа</Value>
    </String>
    <String Id="mlsDJF32UENEBFT3MP2MM6PTGZY4E" SrcKind="1" Version="0">
      <Value Language="ru" NeedsCheck="false" LastModified="2014-11-24T16:27:41.078" Author="ypaliy">&lt;нормальный></Value>
    </String>
    <String Id="mlsEVVBLU26KFEMNHWSJQF2N45NQ4" SrcKind="1" Version="0">
      <Value Language="ru" NeedsCheck="true" LastModified="2013-10-01T10:26:11.656" Author="dsafonov">Ошибка чтения списка доверенных сертификатов из хранилища: </Value>
    </String>
    <String Id="mlsL7INQJUF5BGO3O2DRWUUH55FPQ" SrcKind="1" Version="0">
      <Value Language="ru" NeedsCheck="false" LastModified="2014-11-24T16:27:37.258" Author="ypaliy">Общее</Value>
    </String>
    <String Id="mlsLO6W2ZOBPJBVDNFXM4X3E72HNE" SrcKind="1" Creator="dsafonov" CreationDate="2015-01-28T10:27:13.750" Version="0">
      <Value Language="ru" NeedsCheck="true" LastModified="2015-01-28T10:27:17.561" Author="dsafonov">GetLoad</Value>
    </String>
    <String Id="mlsMRC36O2AA5AF7CXOJGUJXAZKZQ" SrcKind="1" Version="0">
      <Value Language="ru" NeedsCheck="false" LastModified="2014-06-27T11:54:53.091" Author="ypaliy">&lt;любые></Value>
    </String>
    <String Id="mlsT2FPRYFMP5DJFCQFGUKLLDYX2U" SrcKind="1" Version="0">
      <Value Language="ru" NeedsCheck="false" LastModified="2014-10-22T16:58:48.516" Author="ypaliy">Приоритет по умолчанию для ARTE запросов</Value>
    </String>
    <String Id="mlsUDX7BDD4FFHP7GMIFUVFANAMGU" SrcKind="1" Version="0">
      <Value Language="ru" NeedsCheck="false" LastModified="2014-11-24T16:27:28.638" Author="ypaliy">Редактировать</Value>
    </String>
    <String Id="mlsWEUFQOK4OXOBDFKUAAMPGXUWTQ" SrcKind="1" Version="0">
      <Value Language="ru" NeedsCheck="false" LastModified="2014-11-24T16:27:25.108" Author="ypaliy">URI сервиса</Value>
    </String>
    <String Id="mlsWIUFQOK4OXOBDFKUAAMPGXUWTQ" SrcKind="1" Version="0">
      <Value Language="ru" NeedsCheck="false" LastModified="2014-11-24T16:27:21.188" Author="ypaliy">Ид. SAP</Value>
    </String>
    <String Id="mlsWQUFQOK4OXOBDFKUAAMPGXUWTQ" SrcKind="1" Version="0">
      <Value Language="ru" NeedsCheck="false" LastModified="2014-04-28T11:20:41.414" Author="ypaliy">Максимальное число инстанций ARTE</Value>
    </String>
    <String Id="mlsXANRSLAJV5EHBFDC5GOEWWKVNE" SrcKind="1" Version="0">
      <Value Language="ru" NeedsCheck="true" LastModified="2013-10-01T10:26:11.657" Author="dsafonov">Ошибка чтения списка доверенных сертификатов из хранилища: </Value>
    </String>
    <String Id="mlsXK5GM5FUHJH6HB4JWKG3OIIKCY" SrcKind="1" Version="0">
      <Value Language="ru" NeedsCheck="false" LastModified="2014-06-27T11:54:55.234" Author="ypaliy">&lt;любые></Value>
    </String>
    <String Id="mlsZT6Z4PO5SZFVXABXDSGIWQGCWA" SrcKind="3" Creator="dsafonov" CreationDate="2015-01-29T17:35:40.356" Version="0"/>
  </AdsLocalizingBundleDefinition>
</AdsDefinition>